{
  "cate": "6",
  "date": "12æ2æ¥ 7æ18å",
  "datetime": "2017-12-02T07:18",
  "video": "",
  "duration": 0,
  "img": "html/20171202/K10011244041_1712020916_1712020919_01_02.jpg",
  "title": "中国 上海で日本映画紹介 橋本愛さんら登場",
  "summary": "日本の映画への関心が高まっている中国の上海で、特別ゲストとして女優の橋本愛さんが参加し、新作の日本映画を紹介する催しが開かれ、大勢の映画ファンでにぎわいました。",
  "more": "この催しは日中国交正常化からことしで４５年になるのを記念して、中国の上海で１日から３日間の日程で始まりました。<br /><br />期間中、９本の最新の日本映画が上映される予定で、１日は三島由紀夫の小説が原作で、ことし５月に日本で公開された「美しい星」など２本の映画が上映されました。<br /><br />「美しい星」の上映後、会場には吉田大八監督と出演した女優の橋本愛さんが特別ゲストとして登場し、集まった人たちは２人に作品のテーマなどについて日本語で質問していました。<br /><br />催しに参加した女性は「日本の映画はストーリーが生活に近いからおもしろくて、ずっと興味を持っています。これからこうした機会がもっとあればいいと思います」と話していました。<br /><br />中国では外国映画の上映には当局の許可が必要で、日本映画の上映本数も限られていますが、インターネットを通じて触れる人も多く、日本映画への関心が高まっています。<br /><br />また、ことし９月には日本と中国で映画を共同製作する際の手続きを円滑にするための政府間の協定が大筋で合意され、中国で日本映画が期待されています。",
  "body": [
    {
      "title": "",
      "img": "",
      "align": "",
      "text": "",
      "textPos": ""
    }
  ],
  "relationNews": [],
  "relationLink": [],
  "word": [],
  "news_id": "k10011244041000",
  "yyyy": "2017",
  "mm": "12",
  "dd": "02",
  "url": "http://www3.nhk.or.jp/news/html/20171202/k10011244041000.html"
}