{
  "news_id": "k10011264271000",
  "news_prearranged_time": "2017-12-20 15:40:00",
  "title": "八丈島の近くの海でザトウクジラがたくさん見つかる",
  "title_with_ruby": "<ruby>八丈島<rt>はちじょうじま</rt></ruby>の<ruby>近<rt>ちか</rt></ruby>くの<ruby>海<rt>うみ</rt></ruby>でザトウクジラがたくさん<ruby>見<rt>み</rt></ruby>つかる",
  "outline_with_ruby": "<p><ruby>東京<rt>とうきょう</rt></ruby>から<ruby>南<rt>みなみ</rt></ruby>に<a href='javascript:void(0)' class='dicWin' id='id-0000'><ruby>約<rt>やく</rt></ruby></a>２９０ｋｍの<ruby>所<rt>ところ</rt></ruby>にある<ruby>八丈島<rt>はちじょうじま</rt></ruby>の<ruby>近<rt>ちか</rt></ruby>くには、おととしからザトウクジラという<a href='javascript:void(0)' class='dicWin' id='id-0001'><ruby>鯨<rt>くじら</rt></ruby></a>がたくさん<ruby>集<rt>あつ</rt></ruby>まるようになりました。",
  "has_news_web_image": true,
  "has_news_web_movie": false,
  "has_news_easy_image": false,
  "has_news_easy_movie": false,
  "has_news_easy_voice": true,
  "news_web_image_uri": "https://www3.nhk.or.jp/news/html/20171219/../20171219/K10011264271_1712191804_1712191816_01_02.jpg",
  "news_web_movie_uri": "",
  "news_easy_image_uri": "''",
  "news_easy_movie_uri": "''",
  "news_easy_voice_uri": "k10011264271000.mp3",
  "url": "http://www3.nhk.or.jp/news/easy/k10011264271000/k10011264271000.html"
}