{
  "news_id": "k10011257121000",
  "news_prearranged_time": "2017-12-14 15:30:00",
  "title": "京都　舞妓たちが踊りの先生に正月のあいさつをする",
  "title_with_ruby": "<ruby>京都<rt>きょうと</rt></ruby>　<ruby>舞妓<rt>まいこ</rt></ruby>たちが<ruby>踊<rt>おど</rt></ruby>りの<ruby>先生<rt>せんせい</rt></ruby>に<ruby>正月<rt>しょうがつ</rt></ruby>のあいさつをする",
  "outline_with_ruby": "<p><ruby>京都<rt>きょうと</rt></ruby>では１２<ruby>月<rt>がつ</rt></ruby>１３<ruby>日<rt>にち</rt></ruby>は<ruby>正月<rt>しょうがつ</rt></ruby>を<ruby>迎<rt>むか</rt></ruby>える<ruby>準備<rt>じゅんび</rt></ruby>を<ruby>始<rt>はじ</rt></ruby>める<ruby>日<rt>ひ</rt></ruby>です。",
  "has_news_web_image": true,
  "has_news_web_movie": false,
  "has_news_easy_image": false,
  "has_news_easy_movie": false,
  "has_news_easy_voice": true,
  "news_web_image_uri": "https://www3.nhk.or.jp/news/html/20171213/../20171213/K10011257121_1712131307_1712131352_01_02.jpg",
  "news_web_movie_uri": "",
  "news_easy_image_uri": "''",
  "news_easy_movie_uri": "''",
  "news_easy_voice_uri": "k10011257121000.mp3",
  "url": "http://www3.nhk.or.jp/news/easy/k10011257121000/k10011257121000.html"
}